topydo/Commands.py
topydo/__init__.py
topydo/commands/AddCommand.py
topydo/commands/AppendCommand.py
topydo/commands/ArchiveCommand.py
topydo/commands/DeleteCommand.py
topydo/commands/DepCommand.py
topydo/commands/DepriCommand.py
topydo/commands/DoCommand.py
topydo/commands/EditCommand.py
topydo/commands/ExitCommand.py
topydo/commands/ListCommand.py
topydo/commands/ListContextCommand.py
topydo/commands/ListProjectCommand.py
topydo/commands/PostponeCommand.py
topydo/commands/PriorityCommand.py
topydo/commands/RevertCommand.py
topydo/commands/SortCommand.py
topydo/commands/TagCommand.py
topydo/commands/__init__.py
topydo/lib/ChangeSet.py
topydo/lib/Color.py
topydo/lib/Command.py
topydo/lib/Config.py
topydo/lib/DCommand.py
topydo/lib/ExpressionCommand.py
topydo/lib/Filter.py
topydo/lib/Graph.py
topydo/lib/HashListValues.py
topydo/lib/Importance.py
topydo/lib/ListFormat.py
topydo/lib/MultiCommand.py
topydo/lib/PrettyPrinterFilter.py
topydo/lib/ProgressColor.py
topydo/lib/Recurrence.py
topydo/lib/RelativeDate.py
topydo/lib/Sorter.py
topydo/lib/Todo.py
topydo/lib/TodoBase.py
topydo/lib/TodoFile.py
topydo/lib/TodoFileWatched.py
topydo/lib/TodoList.py
topydo/lib/TodoListBase.py
topydo/lib/TodoParser.py
topydo/lib/TopydoString.py
topydo/lib/Utils.py
topydo/lib/Version.py
topydo/lib/View.py
topydo/lib/WriteCommand.py
topydo/lib/__init__.py
topydo/lib/prettyprinters/Colors.py
topydo/lib/prettyprinters/Format.py
topydo/lib/prettyprinters/Numbers.py
topydo/lib/prettyprinters/__init__.py
topydo/lib/printers/Dot.py
topydo/lib/printers/Ical.py
topydo/lib/printers/Json.py
topydo/lib/printers/PrettyPrinter.py
topydo/lib/printers/__init__.py
topydo/ui/CLIApplicationBase.py
topydo/ui/CompleterBase.py
topydo/ui/UILoader.py
topydo/ui/__init__.py
topydo/ui/cli/CLI.py
topydo/ui/cli/__init__.py
topydo/ui/columns/ColumnCompleter.py
topydo/ui/columns/ColumnLayout.py
topydo/ui/columns/CommandLineWidget.py
topydo/ui/columns/CompletionBoxWidget.py
topydo/ui/columns/ConsoleWidget.py
topydo-0.15.dist-info/AUTHORS.md
topydo-0.15.dist-info/LICENSE.txt
topydo-0.15.dist-info/METADATA
topydo-0.15.dist-info/WHEEL
topydo-0.15.dist-info/entry_points.txt
topydo-0.15.dist-info/top_level.txt
topydo-0.15.dist-info/RECORD
